{
  "updated": "2026-03-04T21:10:00Z",
  "meta": {
    "totalSources": 8,
    "totalItems": 9
  },
  "decisionPanels": [
    {
      "title": "Tonight's decision",
      "priority": "high",
      "summary": "Prioritise frictionless review-to-publish and vertical packaging this week; vendor and platform signals both point to speed + mobile-native output as growth levers.",
      "actions": [
        "Adopt a 'review in place' workflow pilot: keep assets in LucidLink/iconik, eliminate side-channel transfers for at least one desk.",
        "Ship a daily vertical package per major story (30-60s + 90-150s) with explicit retention hook in first 2s.",
        "Add localisation experiment: subtitle-first variant + one dubbed variant for a high-probability explainer."
      ]
    },
    {
      "title": "Ops stack watch (iconik/LucidLink/Backlight)",
      "priority": "high",
      "summary": "LucidLink shipped Guest Access + Directory Management API; Backlight is reinforcing vertical/live automation. iconik release pages are anti-bot protected tonight, but indexed snippets indicate panel/plugin and ISG fixes worth direct verification in daylight.",
      "actions": [
        "Validate LucidLink Guest Access against Guardian security policy (external reviewer flow, expiry, revoke paths).",
        "Map Directory Management API to Launcher automation backlog (folder templates + permissions as code).",
        "Run morning manual check of iconik panel/agent/ISG changelogs and log exact versions in MMR risk register."
      ]
    },
    {
      "title": "Audience growth signal",
      "priority": "high",
      "summary": "Official YouTube creator updates and Backlight/Wildmoka data converge on vertical-first discovery and faster social iteration loops.",
      "actions": [
        "Use YouTube Shorts Trends page as daily ideation input for newsroom social producers.",
        "Standardise auto-rezone/vertical framing checklist so each clip has 9:16-first variant.",
        "Track completion rate + shares + saves as primary social health metrics, with CTR as secondary."
      ]
    }
  ],
  "sections": [
    {
      "title": "Vendor Watch: iconik / LucidLink / Backlight",
      "items": [
        {
          "title": "iconik release notes hub (manual verification required; anti-bot blocking observed)",
          "url": "https://app.iconik.io/help/pages/release_notes/",
          "published": "checked 2026-03-04",
          "source": "iconik changelog"
        },
        {
          "title": "iconik Panel snippet: Photoshop/Illustrator 2026 support + Premiere subclip support (from indexed release snippet)",
          "url": "https://app.iconik.io/help/pages/release_notes/panel",
          "published": "recent",
          "source": "iconik changelog"
        },
        {
          "title": "LucidLink January 2026 release: Guest Access + Directory Management API + FQDN proxy support",
          "url": "https://www.lucidlink.com/blog/january-2026-release",
          "published": "2026-01",
          "source": "LucidLink release notes"
        },
        {
          "title": "Backlight resources/news: 2026 Media Stats + NAB 2026 + product update stream",
          "url": "https://www.backlight.co/resources",
          "published": "checked 2026-03-04",
          "source": "Backlight news"
        }
      ]
    },
    {
      "title": "Platform Distribution + Growth",
      "items": [
        {
          "title": "YouTube Creator updates: Shorts Trends page global + new Shorts AI photo motion tool",
          "url": "https://support.google.com/youtube/answer/9072033?hl=en",
          "published": "last 4 weeks",
          "source": "YouTube official"
        },
        {
          "title": "TikTok Discover List 2026 (creator-format trend signal)",
          "url": "https://newsroom.tiktok.com/en-us",
          "published": "2026",
          "source": "TikTok newsroom"
        },
        {
          "title": "Wildmoka: automated social publishing workflow patterns for live clipping",
          "url": "https://www.wildmoka.com/resources/automated-social-media-publishing-how-it-extends-your-broadcast-reach",
          "published": "2026-01-16",
          "source": "Wildmoka"
        }
      ]
    },
    {
      "title": "Newsroom Strategy Signals",
      "items": [
        {
          "title": "2026 Media Stats report: 117% growth in 9:16 publishing since 2024",
          "url": "https://www.iconik.io/media-stats-report-2026",
          "published": "2026",
          "source": "iconik/Backlight"
        },
        {
          "title": "Hybrid storage trend: 71% cloud / 29% on-prem + rising automation volumes",
          "url": "https://www.iconik.io/media-stats-report-2026",
          "published": "2026",
          "source": "iconik/Backlight"
        }
      ]
    }
  ],
  "changes": {
    "previousUpdated": "2026-03-03T22:40:00Z",
    "newCount": 6,
    "removedCount": 13,
    "newItems": [
      {
        "title": "LucidLink January 2026 release (Guest Access + Directory Management API)",
        "url": "https://www.lucidlink.com/blog/january-2026-release",
        "published": "2026-01",
        "source": "LucidLink",
        "section": "Vendor Watch: iconik / LucidLink / Backlight"
      },
      {
        "title": "YouTube Shorts Trends page rollout (official update)",
        "url": "https://support.google.com/youtube/answer/9072033?hl=en",
        "published": "last 4 weeks",
        "source": "YouTube",
        "section": "Platform Distribution + Growth"
      },
      {
        "title": "2026 Media Stats: 117% growth in 9:16 publishing",
        "url": "https://www.iconik.io/media-stats-report-2026",
        "published": "2026",
        "source": "iconik/Backlight",
        "section": "Newsroom Strategy Signals"
      }
    ],
    "summary": "Shift from broad scanning to execution bias: review handoff friction, vertical-first packaging, and automation-ready folder governance are now the highest-leverage near-term bets."
  }
}
